plex_api_client/__init__.py
plex_api_client/_hooks/__init__.py
plex_api_client/_hooks/registration.py
plex_api_client/_hooks/sdkhooks.py
plex_api_client/_hooks/types.py
plex_api_client/_version.py
plex_api_client/activities.py
plex_api_client/authentication.py
plex_api_client/basesdk.py
plex_api_client/butler.py
plex_api_client/collections.py
plex_api_client/content.py
plex_api_client/devices.py
plex_api_client/download_queue.py
plex_api_client/dvrs.py
plex_api_client/epg.py
plex_api_client/events.py
plex_api_client/general.py
plex_api_client/httpclient.py
plex_api_client/hubs.py
plex_api_client/library.py
plex_api_client/library_collections.py
plex_api_client/library_playlists.py
plex_api_client/live_tv.py
plex_api_client/log.py
plex_api_client/models/__init__.py
plex_api_client/models/components/__init__.py
plex_api_client/models/components/accepts.py
plex_api_client/models/components/advancedsubtitles.py
plex_api_client/models/components/boolint.py
plex_api_client/models/components/channel.py
plex_api_client/models/components/channelmapping.py
plex_api_client/models/components/composite.py
plex_api_client/models/components/device.py
plex_api_client/models/components/directory.py
plex_api_client/models/components/dvrrequesthandler_slash_get_responses_200.py
plex_api_client/models/components/filter_.py
plex_api_client/models/components/get_responses_200.py
plex_api_client/models/components/historyall_get_responses_200.py
plex_api_client/models/components/hub.py
plex_api_client/models/components/image.py
plex_api_client/models/components/items.py
plex_api_client/models/components/librarysection.py
plex_api_client/models/components/librarysections.py
plex_api_client/models/components/lineup.py
plex_api_client/models/components/location.py
plex_api_client/models/components/media.py
plex_api_client/models/components/mediacontainer.py
plex_api_client/models/components/mediacontainerwithartwork.py
plex_api_client/models/components/mediacontainerwithdecision.py
plex_api_client-0.33.2.dist-info/METADATA
plex_api_client-0.33.2.dist-info/WHEEL
plex_api_client-0.33.2.dist-info/licenses/LICENSE.md
plex_api_client-0.33.2.dist-info/RECORD
